qtstyles/__init__.py
qtstyles/demo.py
qtstyles/errors.py
qtstyles/picker.py
qtstyles/sheet.py
qtstyles/widget.py
qtstyles/style_sheets/__init__.py
qtstyles/style_sheets/breeze-dark.qss
qtstyles/style_sheets/breeze-light.qss
qtstyles/style_sheets/coffee.qss
qtstyles/style_sheets/dark-blue.qss
qtstyles/style_sheets/dark-green.qss
qtstyles/style_sheets/dark-orange.qss
qtstyles/style_sheets/default.qss
qtstyles/style_sheets/light-blue.qss
qtstyles/style_sheets/light-green.qss
qtstyles/style_sheets/light-orange.qss
qtstyles/style_sheets/material-blue.qss
qtstyles/style_sheets/pagefold.qss
qtstyles/style_sheets/qdark.qss
qtstyles/style_sheets/qtdark.qss
qtstyles-0.0.2.dist-info/METADATA
qtstyles-0.0.2.dist-info/RECORD
qtstyles-0.0.2.dist-info/WHEEL
qtstyles-0.0.2.dist-info/top_level.txt
