Metadata-Version: 2.1
Name: qtstyles
Version: 0.0.2
Summary: A collection of Qt style sheets and helpful classes for applying them.
Home-page: https://github.com/simongarisch/qtstyles
Author: Simon Garisch
Author-email: gatman946@gmail.com
License: UNKNOWN
Platform: UNKNOWN
Requires-Dist: QtPy (>=1.4.1)
